bgq.py
webint_jobs/__init__.py
webint_jobs/templates/__init__.py
webint_jobs/templates/by_module.html
webint_jobs/templates/by_object.html
webint_jobs/templates/index.html
webint_jobs/templates/job.html
webint_jobs/templates/run.html
webint_jobs/templates/schedules.html
webint_jobs/templates/slow.html
bgq-0.1.7.dist-info/METADATA
bgq-0.1.7.dist-info/entry_points.txt
bgq-0.1.7.dist-info/WHEEL
bgq-0.1.7.dist-info/RECORD
