Metadata-Version: 2.1
Name: bgq
Version: 0.1.7
Summary: a simple asynchronous background job queue
Home-page: https://ragt.ag/code/projects/bgq
License: AGPL-3.0-or-later
Author: Angelo Gladding
Author-email: angelo@ragt.ag
Requires-Python: >=3.10,<3.11
Classifier: License :: OSI Approved :: GNU Affero General Public License v3 or later (AGPLv3+)
Classifier: Programming Language :: Python :: 3
Classifier: Programming Language :: Python :: 3.10
Requires-Dist: sqlyte (>=0.1.1,<0.2.0)
Requires-Dist: txtint (>=0.1.2,<0.2.0)
Requires-Dist: webagt (>=0.1.2,<0.2.0)
Requires-Dist: webint (>=0.1.59,<0.2.0)
Project-URL: Documentation, https://ragt.ag/code/projects/bgq/api
Project-URL: Repository, https://ragt.ag/code/projects/bgq.git
